<annotation>
	<folder>JPEGImage</folder>
	<filename>000387.jpg</filename>
	<path>D:\1111111111D盘的桌面\111图片训练集\JPEGImage\000387.jpg</path>
	<source>
		<database>Unknown</database>
	</source>
	<size>
		<width>4096</width>
		<height>512</height>
		<depth>3</depth>
	</size>
	<segmented>0</segmented>
	<object>
		<name>window</name>
		<pose>Unspecified</pose>
		<truncated>0</truncated>
		<difficult>0</difficult>
		<bndbox>
			<xmin>107</xmin>
			<ymin>167</ymin>
			<xmax>133</xmax>
			<ymax>205</ymax>
		</bndbox>
	</object>
	<object>
		<name>window</name>
		<pose>Unspecified</pose>
		<truncated>0</truncated>
		<difficult>0</difficult>
		<bndbox>
			<xmin>210</xmin>
			<ymin>243</ymin>
			<xmax>236</xmax>
			<ymax>281</ymax>
		</bndbox>
	</object>
	<object>
		<name>window</name>
		<pose>Unspecified</pose>
		<truncated>0</truncated>
		<difficult>0</difficult>
		<bndbox>
			<xmin>110</xmin>
			<ymin>232</ymin>
			<xmax>136</xmax>
			<ymax>270</ymax>
		</bndbox>
	</object>
	<object>
		<name>window</name>
		<pose>Unspecified</pose>
		<truncated>0</truncated>
		<difficult>0</difficult>
		<bndbox>
			<xmin>266</xmin>
			<ymin>185</ymin>
			<xmax>292</xmax>
			<ymax>223</ymax>
		</bndbox>
	</object>
	<object>
		<name>window</name>
		<pose>Unspecified</pose>
		<truncated>0</truncated>
		<difficult>0</difficult>
		<bndbox>
			<xmin>208</xmin>
			<ymin>177</ymin>
			<xmax>243</xmax>
			<ymax>219</ymax>
		</bndbox>
	</object>
	<object>
		<name>window</name>
		<pose>Unspecified</pose>
		<truncated>0</truncated>
		<difficult>0</difficult>
		<bndbox>
			<xmin>271</xmin>
			<ymin>246</ymin>
			<xmax>297</xmax>
			<ymax>284</ymax>
		</bndbox>
	</object>
	<object>
		<name>window</name>
		<pose>Unspecified</pose>
		<truncated>0</truncated>
		<difficult>0</difficult>
		<bndbox>
			<xmin>965</xmin>
			<ymin>268</ymin>
			<xmax>1184</xmax>
			<ymax>423</ymax>
		</bndbox>
	</object>
	<object>
		<name>window</name>
		<pose>Unspecified</pose>
		<truncated>0</truncated>
		<difficult>0</difficult>
		<bndbox>
			<xmin>1529</xmin>
			<ymin>369</ymin>
			<xmax>1672</xmax>
			<ymax>470</ymax>
		</bndbox>
	</object>
	<object>
		<name>window</name>
		<pose>Unspecified</pose>
		<truncated>0</truncated>
		<difficult>0</difficult>
		<bndbox>
			<xmin>1270</xmin>
			<ymin>305</ymin>
			<xmax>1489</xmax>
			<ymax>460</ymax>
		</bndbox>
	</object>
	<object>
		<name>window</name>
		<pose>Unspecified</pose>
		<truncated>0</truncated>
		<difficult>0</difficult>
		<bndbox>
			<xmin>2505</xmin>
			<ymin>420</ymin>
			<xmax>2781</xmax>
			<ymax>510</ymax>
		</bndbox>
	</object>
	<object>
		<name>window</name>
		<pose>Unspecified</pose>
		<truncated>0</truncated>
		<difficult>0</difficult>
		<bndbox>
			<xmin>2821</xmin>
			<ymin>356</ymin>
			<xmax>2961</xmax>
			<ymax>500</ymax>
		</bndbox>
	</object>
	<object>
		<name>window</name>
		<pose>Unspecified</pose>
		<truncated>0</truncated>
		<difficult>0</difficult>
		<bndbox>
			<xmin>3289</xmin>
			<ymin>437</ymin>
			<xmax>3354</xmax>
			<ymax>487</ymax>
		</bndbox>
	</object>
	<object>
		<name>window</name>
		<pose>Unspecified</pose>
		<truncated>0</truncated>
		<difficult>0</difficult>
		<bndbox>
			<xmin>3397</xmin>
			<ymin>437</ymin>
			<xmax>3462</xmax>
			<ymax>498</ymax>
		</bndbox>
	</object>
	<object>
		<name>window</name>
		<pose>Unspecified</pose>
		<truncated>0</truncated>
		<difficult>0</difficult>
		<bndbox>
			<xmin>3490</xmin>
			<ymin>434</ymin>
			<xmax>3537</xmax>
			<ymax>482</ymax>
		</bndbox>
	</object>
</annotation>
